py_cxx_builder/__init__.py
py_cxx_builder/__main__.py
py_cxx_builder/cli.py
py_cxx_builder/py.typed
py_cxx_builder-0.1.1.dist-info/licenses/LICENSE
py_cxx_builder-0.1.1.dist-info/METADATA
py_cxx_builder-0.1.1.dist-info/WHEEL
py_cxx_builder-0.1.1.dist-info/top_level.txt
py_cxx_builder-0.1.1.dist-info/RECORD
