Metadata-Version: 2.4
Name: py-cxx-builder
Version: 0.1.1
Summary: Build C++ extensions for Python with cross-platform support (MSVC/GCC)
Author-email: swigger <swigger@gmail.com>
License-Expression: MIT
Project-URL: Homepage, https://github.com/swigger/py-cxx-builder
Project-URL: Repository, https://github.com/swigger/py-cxx-builder
Project-URL: Issues, https://github.com/swigger/py-cxx-builder/issues
Keywords: c++,extension,build,setuptools,msvc,gcc
Classifier: Development Status :: 4 - Beta
Classifier: Intended Audience :: Developers
Classifier: Operating System :: OS Independent
Classifier: Operating System :: Microsoft :: Windows
Classifier: Operating System :: POSIX :: Linux
Classifier: Operating System :: MacOS
Classifier: Programming Language :: Python :: 3
Classifier: Programming Language :: Python :: 3.10
Classifier: Programming Language :: Python :: 3.11
Classifier: Programming Language :: Python :: 3.12
Classifier: Programming Language :: Python :: 3.13
Classifier: Programming Language :: C++
Classifier: Topic :: Software Development :: Build Tools
Classifier: Topic :: Software Development :: Compilers
Requires-Python: >=3.10
License-File: LICENSE
Requires-Dist: setuptools>=61.0
Requires-Dist: tomli>=2.0; python_version < "3.11"
Provides-Extra: dev
Requires-Dist: pytest>=7.0; extra == "dev"
Requires-Dist: pytest-cov>=4.0; extra == "dev"
Dynamic: license-file
